h2hdb_downloader/__init__.py
h2hdb_downloader/downloader.py
h2hdb_downloader/py.typed
h2hdb_downloader-0.0.9.dist-info/licenses/LICENSE
h2hdb_downloader-0.0.9.dist-info/METADATA
h2hdb_downloader-0.0.9.dist-info/WHEEL
h2hdb_downloader-0.0.9.dist-info/top_level.txt
h2hdb_downloader-0.0.9.dist-info/RECORD
