Metadata-Version: 2.4
Name: h2hdb-downloader
Version: 0.0.9
Summary: Download gallery and insert into h2hdb
Author: Kuan-Lun Wang
License: GNU Affero General Public License v3
Project-URL: Homepage, https://github.com/Kuan-Lun/h2hdb-downloader
Project-URL: Source, https://github.com/Kuan-Lun/h2hdb-downloader
Project-URL: Tracker, https://github.com/Kuan-Lun/h2hdb-downloader/issues
Classifier: Development Status :: 3 - Alpha
Classifier: Intended Audience :: Developers
Classifier: Operating System :: OS Independent
Classifier: License :: OSI Approved :: GNU Affero General Public License v3 or later (AGPLv3+)
Classifier: Programming Language :: Python :: 3.13
License-File: LICENSE
Requires-Dist: h2hdb>=0.9.1.9
Requires-Dist: hbrowser>=0.9.8
Dynamic: license-file
